pypontem/__init__.py
pypontem/ppl/.gitkeep
pypontem/ppl/__init__.py
pypontem/ppl/pplparser.py
pypontem/tpl/.gitkeep
pypontem/tpl/__init__.py
pypontem/tpl/tplparser.py
pypontem/utils/__init__.py
pypontem/utils/unit_conversion.py
pypontem/utils/units.yaml
pypontem-1.1.5.dist-info/LICENSE
pypontem-1.1.5.dist-info/METADATA
pypontem-1.1.5.dist-info/WHEEL
pypontem-1.1.5.dist-info/top_level.txt
pypontem-1.1.5.dist-info/RECORD
