Metadata-Version: 2.1
Name: pypontem
Version: 1.1.5
Summary: The one-stop python toolkit for Flow Assurance workflows
Home-page: https://github.com/Pontem-Analytics/pypontem_public/tree/main
Requires-Python: >=3.11
License-File: LICENSE
Requires-Dist: pandas>=2.2.0
Requires-Dist: pint>=0.23
Requires-Dist: PyYAML>=6.0.2
